{
  "_format": "hh-sol-cache-2",
  "files": {
    "/workspace/contracts/MultiSigWallet.sol": {
      "lastModificationDate": 1758718764510,
      "contentHash": "0be0d0572810d160843f06f42445251f",
      "sourceName": "contracts/MultiSigWallet.sol",
      "solcConfig": {
        "version": "0.8.24",
        "settings": {
          "optimizer": {
            "enabled": true,
            "runs": 200
          },
          "evmVersion": "paris",
          "outputSelection": {
            "*": {
              "*": [
                "abi",
                "evm.bytecode",
                "evm.deployedBytecode",
                "evm.methodIdentifiers",
                "metadata"
              ],
              "": [
                "ast"
              ]
            }
          }
        }
      },
      "imports": [],
      "versionPragmas": [
        "^0.8.24"
      ],
      "artifacts": [
        "MultiSigWallet"
      ]
    }
  }
}
